<?xml version="1.0" encoding="UTF-8"?>
<objects serializationModel="Studio.02.02.00">
	<object class="AudioFile" id="{2525f92d-ce81-4d56-af82-5d4d09a36965}">
		<property name="assetPath">
			<value>Body loop.wav</value>
		</property>
		<property name="isStreaming">
			<value>true</value>
		</property>
		<property name="frequencyInKHz">
			<value>48</value>
		</property>
		<property name="channelCount">
			<value>2</value>
		</property>
		<property name="length">
			<value>70.106687500000007</value>
		</property>
		<relationship name="masterAssetFolder">
			<destination>{a5e1c0ea-8cfe-439a-bbcb-ade5a6538487}</destination>
		</relationship>
	</object>
</objects>
